<?xml version="1.0" encoding="UTF-8"?>
<objects serializationModel="Studio.02.02.00">
	<object class="AudioFile" id="{e70b2bae-6e3d-44d6-91d9-479296d591ee}">
		<property name="assetPath">
			<value>Big-Band-Swingin_Looping.mp3</value>
		</property>
		<property name="isStreaming">
			<value>true</value>
		</property>
		<property name="frequencyInKHz">
			<value>44.0999985</value>
		</property>
		<property name="channelCount">
			<value>2</value>
		</property>
		<property name="length">
			<value>76.826122448979589</value>
		</property>
		<relationship name="masterAssetFolder">
			<destination>{743f847a-e0d1-421c-b27e-4c834fa93b8a}</destination>
		</relationship>
	</object>
</objects>
